{
  "slug": "purpose-wholeness-20260611",
  "theme": "purpose",
  "hook": "Your wholeness was never a deliverable.",
  "posted": false,
  "slide_urls": [
    "https://beyondelevation.com/assets/ig-cloud/purpose-wholeness-20260611/slide_1.jpg",
    "https://beyondelevation.com/assets/ig-cloud/purpose-wholeness-20260611/slide_2.jpg",
    "https://beyondelevation.com/assets/ig-cloud/purpose-wholeness-20260611/slide_3.jpg",
    "https://beyondelevation.com/assets/ig-cloud/purpose-wholeness-20260611/slide_4.jpg",
    "https://beyondelevation.com/assets/ig-cloud/purpose-wholeness-20260611/slide_5.jpg",
    "https://beyondelevation.com/assets/ig-cloud/purpose-wholeness-20260611/slide_6.jpg"
  ],
  "caption": "Your wholeness was never a deliverable.\n\nYou spent years becoming better at your job and further from yourself. Every review measured your output but never asked what you actually wanted from this life.\n\nAI is now handling the output. What remains is the question the job always crowded out: what do I want? For most workers, that question has been buried for 15 years. That is not a breakdown. It is the first honest moment of your career.\n\nDavid Whyte left marine biology to become a poet. Fortune 500 executives now pay him to sit in silence and read verse. That is the only work AI cannot replace.\n\nStart there.\n\n#postai #futureofwork #meaningfulwork",
  "queued_at": "2026-06-11T16:36:00Z"
}
